{
  "project_info": {
    "project_number": "447314326003",
    "firebase_url": "https://rumusbangun.firebaseio.com",
    "project_id": "rumusbangun",
    "storage_bucket": "rumusbangun.appspot.com"
  },
  "client": [
    {
      "client_info": {
        "mobilesdk_app_id": "1:447314326003:android:158f34e6df8172b61c6286",
        "android_client_info": {
          "package_name": "com.agusw.notesapp"
        }
      },
      "oauth_client": [
        {
          "client_id": "447314326003-soahtirrs7ob4kt7hh5t7uvq5a7epth7.apps.googleusercontent.com",
          "client_type": 1,
          "android_info": {
            "package_name": "com.agusw.notesapp",
            "certificate_hash": "0bb1266ede7777aaae0ee4b02f4febbda8d9f1e0"
          }
        },
        {
          "client_id": "447314326003-r2l5img7rt4es73s7t522ihp6i6cs8qa.apps.googleusercontent.com",
          "client_type": 3
        }
      ],
      "api_key": [
        {
          "current_key": "AIzaSyCE2MW2AO8NTP541IW3nmFMQXxN6VmWG9I"
        }
      ],
      "services": {
        "appinvite_service": {
          "other_platform_oauth_client": [
            {
              "client_id": "447314326003-r2l5img7rt4es73s7t522ihp6i6cs8qa.apps.googleusercontent.com",
              "client_type": 3
            }
          ]
        }
      }
    },
    {
      "client_info": {
        "mobilesdk_app_id": "1:447314326003:android:64923ba756d24d37",
        "android_client_info": {
          "package_name": "com.agusw.rumusbangun"
        }
      },
      "oauth_client": [
        {
          "client_id": "447314326003-fr6gs3a62ogjt83f6551q9kbv7j1r6g3.apps.googleusercontent.com",
          "client_type": 1,
          "android_info": {
            "package_name": "com.agusw.rumusbangun",
            "certificate_hash": "37c6a481647b8e87cb3b042b4cb16a56655c252c"
          }
        },
        {
          "client_id": "447314326003-r2l5img7rt4es73s7t522ihp6i6cs8qa.apps.googleusercontent.com",
          "client_type": 3
        }
      ],
      "api_key": [
        {
          "current_key": "AIzaSyCE2MW2AO8NTP541IW3nmFMQXxN6VmWG9I"
        }
      ],
      "services": {
        "appinvite_service": {
          "other_platform_oauth_client": [
            {
              "client_id": "447314326003-r2l5img7rt4es73s7t522ihp6i6cs8qa.apps.googleusercontent.com",
              "client_type": 3
            }
          ]
        }
      }
    },
    {
      "client_info": {
        "mobilesdk_app_id": "1:447314326003:android:97528fff3d24cb001c6286",
        "android_client_info": {
          "package_name": "com.example.testcamera"
        }
      },
      "oauth_client": [
        {
          "client_id": "447314326003-00tpt1vi0s6fvb2inf75v0g8qk2n0s0v.apps.googleusercontent.com",
          "client_type": 1,
          "android_info": {
            "package_name": "com.example.testcamera",
            "certificate_hash": "57d3d11f9f4d77a490e7c1f925b884cc89b2cd7b"
          }
        },
        {
          "client_id": "447314326003-r2l5img7rt4es73s7t522ihp6i6cs8qa.apps.googleusercontent.com",
          "client_type": 3
        }
      ],
      "api_key": [
        {
          "current_key": "AIzaSyCE2MW2AO8NTP541IW3nmFMQXxN6VmWG9I"
        }
      ],
      "services": {
        "appinvite_service": {
          "other_platform_oauth_client": [
            {
              "client_id": "447314326003-r2l5img7rt4es73s7t522ihp6i6cs8qa.apps.googleusercontent.com",
              "client_type": 3
            }
          ]
        }
      }
    }
  ],
  "configuration_version": "1"
}